dynamic_factory.py
dynamic_factory-0.1.9.dist-info/METADATA
dynamic_factory-0.1.9.dist-info/WHEEL
dynamic_factory-0.1.9.dist-info/RECORD
