Metadata-Version: 2.1
Name: dynamic-factory
Version: 0.1.9
Summary: This module contain dynamic implementations of factory pattern
License: Apache-2.0
Author: Wojciech Bogobowicz
Author-email: wojciech.bogobowicz@gmail.com
Requires-Python: >=3.7
Classifier: License :: OSI Approved :: Apache Software License
Classifier: Programming Language :: Python :: 3
Classifier: Programming Language :: Python :: 3.7
Classifier: Programming Language :: Python :: 3.8
Classifier: Programming Language :: Python :: 3.9
Classifier: Programming Language :: Python :: 3.10
Classifier: Programming Language :: Python :: 3.11
